cli.py
MFA/__init__.py
MFA/mfa.py
cli_aws_mfa-0.0.10.dist-info/LICENSE
cli_aws_mfa-0.0.10.dist-info/METADATA
cli_aws_mfa-0.0.10.dist-info/WHEEL
cli_aws_mfa-0.0.10.dist-info/entry_points.txt
cli_aws_mfa-0.0.10.dist-info/top_level.txt
cli_aws_mfa-0.0.10.dist-info/RECORD
