Metadata-Version: 2.1
Name: cli-aws-mfa
Version: 0.0.10
Summary: AWS CLI MFA - Easily Manage Session Token
Author: imajeetyadav (Ajeet Yadav)
Author-email: <hello@codingprotocols.com>
Keywords: aws,mfa,virtual
License-File: LICENSE
Requires-Dist: click
Requires-Dist: boto3
